{"title":"Entity: Article note structure (article)","hash":"d048a4f67aa9d5f044dac6ff8d1b97b2","updated":"2026-03-09T23:49:17-05:00","created":"2026-03-09T23:49:17-05:00","accessed":"2026-03-09T23:49:17-05:00","lead":"Article notes summarise external content relevant to partner dancing -- YouTube videos, blog posts, workshop recordings, and instructional material. Each article note captures the source, key takeaways, and connections to [concepts](../8) and [moves](../16) in this KEG. For original step-by-step instructions, use a [guide](../10) instead.","links":["5","8","10","16"]}